crowdbox
