Metadata-Version: 1.1
Name: crowdbox
Version: 0.0.3
Summary: Command-line Client for Crowdbox
Home-page: http://crowdbox.io
Author: Tom Buckley-Houston
Author-email: tom@tombh.co.uk
License: Copyright 2013 Crowdbox
